[
  {
    "data": "svhn",
    "use_bias": true,
    "hidden_layers": [
      {"nr_neurons": 200, "type": "hidden", "activation": "relu", "init": "he"},
      {"nr_neurons": 200, "type": "dropout", "prob": 0.4},
      {"nr_neurons": 200, "type": "hidden", "activation": "relu", "init": "he"}
    ],
    "out_activ": "softmax",
    "loss": "categorical_cross_entropy",
    "out_init": "he",
    "online": false,
    "batch_size": 1000,
    "learning_rate":0.01,
    "epochs": 5
  },
   {
    "data": "svhn",
    "use_bias": true,
    "hidden_layers": [
      {"nr_neurons": 30, "type": "hidden", "activation": "relu", "init": "he"},
      {"nr_neurons": 30, "type": "dropout", "prob": 0.4},
      {"nr_neurons": 20, "type": "hidden", "activation": "relu", "init": "he"}
    ],
    "out_activ": "softmax",
    "loss": "categorical_cross_entropy",
    "out_init": "he",
    "online": false,
    "batch_size": 1000,
    "learning_rate":0.01,
    "epochs": 5
  }
]